{"cameraMode":{"drawMode":0,"name":"Shaded","section":"Shading Mode"},"sceneLighting":true,"audioPlay":false,"sceneViewState":{"showFog":true,"showMaterialUpdate":false,"showSkybox":true,"showFlares":true,"showImageEffects":true,"showParticleSystems":true},"in2DMode":false,"pivot":{"x":1.6926082372665406,"y":-1.2144138813018799,"z":7.257838249206543},"rotation":{"x":-0.07224541157484055,"y":0.006580047309398651,"z":-0.0004765957419294864,"w":-0.9973651170730591},"size":21.437931060791017,"orthographic":false}